[
  {
    "序號": "1",
    "論文名稱": "從國際法論我國海洋環境保護之相關法制",
    "研究生": "洪伯昇",
    "指導教授": "姜皇池",
    "校院名稱": "中央警察大學",
    "系所名稱": "水上警察研究所",
    "學位類別": "碩士",
    "畢業學年度": "88",
    "論文出版年": "2000"
  },
  {
    "序號": "2",
    "論文名稱": "百噸級巡防艇籌建作業流程之研究",
    "研究生": "黃宣凱",
    "指導教授": "吳東明",
    "校院名稱": "中央警察大學",
    "系所名稱": "水上警察研究所",
    "學位類別": "碩士",
    "畢業學年度": "88",
    "論文出版年": "2000"
  },
  {
    "序號": "3",
    "論文名稱": "海巡船艇海損及其維修作業之探討",
    "研究生": "江東興",
    "指導教授": "吳東明",
    "校院名稱": "中央警察大學",
    "系所名稱": "水上警察研究所",
    "學位類別": "碩士",
    "畢業學年度": "88",
    "論文出版年": "2000"
  },
  {
    "序號": "4",
    "論文名稱": "海洋巡防任務的鑑艇規劃",
    "研究生": "歐凌嘉",
    "指導教授": "吳東明",
    "校院名稱": "中央警察大學",
    "系所名稱": "水上警察研究所",
    "學位類別": "碩士",
    "畢業學年度": "88",
    "論文出版年": "2000"
  },
  {
    "序號": "5",
    "論文名稱": "海難事故搜救　處理與證據調查之分析研究",
    "研究生": "洪挬論",
    "指導教授": "陳彥宏　姜皇池",
    "校院名稱": "中央警察大學",
    "系所名稱": "水上警察研究所",
    "學位類別": "碩士",
    "畢業學年度": "88",
    "論文出版年": "2000"
  },
  {
    "序號": "6",
    "論文名稱": "大陸人民海上偷渡偵查勤務研究",
    "研究生": "呂岳城",
    "指導教授": "吳學燕　陳佳德",
    "校院名稱": "中央警察大學",
    "系所名稱": "水上警察研究所",
    "學位類別": "碩士",
    "畢業學年度": "88",
    "論文出版年": "1996"
  },
  {
    "序號": "7",
    "論文名稱": "海洋巡防總局指管通信系統整合與發展之研究",
    "研究生": "吳金河",
    "指導教授": "劉春暉",
    "校院名稱": "中央警察大學",
    "系所名稱": "水上警察研究所",
    "學位類別": "碩士",
    "畢業學年度": "88",
    "論文出版年": "1999"
  },
  {
    "序號": "8",
    "論文名稱": "國際海洋法上群島制度之研究",
    "研究生": "李昌原",
    "指導教授": "姜皇池",
    "校院名稱": "中央警察大學",
    "系所名稱": "水上警察研究所",
    "學位類別": "碩士",
    "畢業學年度": "88",
    "論文出版年": "1999"
  },
  {
    "序號": "9",
    "論文名稱": "海上船舶油污排洩處理設備與人員訓練之初探",
    "研究生": "張春水",
    "指導教授": "陳彥宏\n陳先文",
    "校院名稱": "中央警察大學",
    "系所名稱": "水上警察研究所",
    "學位類別": "碩士",
    "畢業學年度": "88",
    "論文出版年": "1999"
  },
  {
    "序號": "10",
    "論文名稱": "電腦輔助港口國管制之船舶查驗系統建置",
    "研究生": "王需楓",
    "指導教授": "吳東明",
    "校院名稱": "中央警察大學",
    "系所名稱": "水上警察研究所",
    "學位類別": "碩士",
    "畢業學年度": "89",
    "論文出版年": "2002"
  },
  {
    "序號": "11",
    "論文名稱": "海巡船艇維修暨後勤管理之探討",
    "研究生": "倪志忠",
    "指導教授": "吳東明",
    "校院名稱": "中央警察大學",
    "系所名稱": "水上警察研究所",
    "學位類別": "碩士",
    "畢業學年度": "89",
    "論文出版年": "2002"
  },
  {
    "序號": "12",
    "論文名稱": "海岸巡防組織機制建立之研究",
    "研究生": "蔡崇謀",
    "指導教授": "劉光華　吳東明",
    "校院名稱": "中央警察大學",
    "系所名稱": "水上警察研究所",
    "學位類別": "碩士",
    "畢業學年度": "89",
    "論文出版年": "2002"
  },
  {
    "序號": "13",
    "論文名稱": "互動式海事調查資料庫之建構",
    "研究生": "蘇克明",
    "指導教授": "陳彥宏\n姜皇池",
    "校院名稱": "中央警察大學",
    "系所名稱": "水上警察研究所",
    "學位類別": "碩士",
    "畢業學年度": "89",
    "論文出版年": "2002"
  },
  {
    "序號": "14",
    "論文名稱": "海洋巡防艇壽期之振動問題防制對策",
    "研究生": "胡誠友",
    "指導教授": "吳東明",
    "校院名稱": "中央警察大學",
    "系所名稱": "水上警察研究所",
    "學位類別": "碩士",
    "畢業學年度": "89",
    "論文出版年": "2002"
  },
  {
    "序號": "15",
    "論文名稱": "從公共政策形成模式探討我國水上警察教育政策制定之研究",
    "研究生": "彭塞雲",
    "指導教授": "陳佳德\n吳東明",
    "校院名稱": "中央警察大學",
    "系所名稱": "水上警察研究所",
    "學位類別": "碩士",
    "畢業學年度": "90",
    "論文出版年": "2002"
  },
  {
    "序號": "16",
    "論文名稱": "從歷史經驗論當前海巡勤務之策略作為",
    "研究生": "龔光宇",
    "指導教授": "鍾桐生\n吳東銘",
    "校院名稱": "中央警察大學",
    "系所名稱": "水上警察研究所",
    "學位類別": "碩士",
    "畢業學年度": "90",
    "論文出版年": "2002"
  },
  {
    "序號": "17",
    "論文名稱": "我國海域遊憩活動管理制度之研究",
    "研究生": "趙瑞華",
    "指導教授": "陳先文",
    "校院名稱": "中央警察大學",
    "系所名稱": "水上警察研究所",
    "學位類別": "碩士",
    "畢業學年度": "90",
    "論文出版年": "2002"
  },
  {
    "序號": "18",
    "論文名稱": "我國海事安全行政系統之研究",
    "研究生": "謝弘毅",
    "指導教授": "陳彥宏　陳先文",
    "校院名稱": "中央警察大學",
    "系所名稱": "水上警察研究所",
    "學位類別": "碩士",
    "畢業學年度": "90",
    "論文出版年": "2002"
  },
  {
    "序號": "19",
    "論文名稱": "我國海上搜救作業與訓練規畫之研究",
    "研究生": "陳坤宗",
    "指導教授": "吳東明",
    "校院名稱": "中央警察大學",
    "系所名稱": "水上警察研究所",
    "學位類別": "碩士",
    "畢業學年度": "90",
    "論文出版年": "2002"
  },
  {
    "序號": "20",
    "論文名稱": "我國海岸巡防署海洋環境污染防治任務之執法策略規畫研析",
    "研究生": "張育嘉",
    "指導教授": "吳東明",
    "校院名稱": "中央警察大學",
    "系所名稱": "水上警察研究所",
    "學位類別": "碩士",
    "畢業學年度": "90",
    "論文出版年": "2002"
  },
  {
    "序號": "21",
    "論文名稱": "全球海上船舶遭遇海盜行為與持械搶劫之研究",
    "研究生": "陳護元",
    "指導教授": "陳彥宏　陳先文",
    "校院名稱": "中央警察大學",
    "系所名稱": "水上警察研究所",
    "學位類別": "碩士",
    "畢業學年度": "90",
    "論文出版年": "2002"
  },
  {
    "序號": "22",
    "論文名稱": "我國海上交通安全管理的應用科技系統整合研究",
    "研究生": "葛錫安",
    "指導教授": "吳東明",
    "校院名稱": "中央警察大學",
    "系所名稱": "水上警察研究所",
    "學位類別": "碩士",
    "畢業學年度": "90",
    "論文出版年": "2002"
  },
  {
    "序號": "23",
    "論文名稱": "由國際法檢視我國領海基點基線之主張",
    "研究生": "洪智銘",
    "指導教授": "陳佳德　姜皇池",
    "校院名稱": "中央警察大學",
    "系所名稱": "水上警察研究所",
    "學位類別": "碩士",
    "畢業學年度": "90",
    "論文出版年": "2002"
  },
  {
    "序號": "24",
    "論文名稱": "建構我國海巡人員考訓體系之研究---以海洋巡防總局為例",
    "研究生": "陳慶昌",
    "指導教授": "朱金池　吳東明",
    "校院名稱": "中央警察大學",
    "系所名稱": "水上警察研究所",
    "學位類別": "碩士",
    "畢業學年度": "90",
    "論文出版年": "2002"
  },
  {
    "序號": "25",
    "論文名稱": "我國漁船海上安檢執法策略",
    "研究生": "楊均賢",
    "指導教授": "吳東明",
    "校院名稱": "中央警察大學",
    "系所名稱": "水上警察研究所",
    "學位類別": "碩士",
    "畢業學年度": "91",
    "論文出版年": "2004"
  },
  {
    "序號": "26",
    "論文名稱": "國際漁業規範之研究-以台灣之參與和執行為探討主軸",
    "研究生": "詹啟明",
    "指導教授": "姜皇池　陳佳德",
    "校院名稱": "中央警察大學",
    "系所名稱": "水上警察研究所",
    "學位類別": "碩士",
    "畢業學年度": "91",
    "論文出版年": "2003"
  },
  {
    "序號": "27",
    "論文名稱": "海岸巡防署海上交通安全管理執法實務規畫研析",
    "研究生": "羅弘熙",
    "指導教授": "吳東明",
    "校院名稱": "中央警察大學",
    "系所名稱": "水上警察研究所",
    "學位類別": "碩士",
    "畢業學年度": "91",
    "論文出版年": "2003"
  },
  {
    "序號": "28",
    "論文名稱": "應用資料包絡分析法於海岸巡防組織績效評估之研究--以海洋巡防總局為例",
    "研究生": "鐘誌誠",
    "指導教授": "林曾祥　陳佳德",
    "校院名稱": "中央警察大學",
    "系所名稱": "水上警察研究所",
    "學位類別": "碩士",
    "畢業學年度": "91",
    "論文出版年": "2003"
  },
  {
    "序號": "29",
    "論文名稱": "海巡署海難搜救資源整合規畫",
    "研究生": "曾忠智",
    "指導教授": "吳東明",
    "校院名稱": "中央警察大學",
    "系所名稱": "水上警察研究所",
    "學位類別": "碩士",
    "畢業學年度": "91",
    "論文出版年": "2003"
  },
  {
    "序號": "30",
    "論文名稱": "中美海難救助作業系統實務之比較研究",
    "研究生": "李松樵",
    "指導教授": "吳東明",
    "校院名稱": "中央警察大學",
    "系所名稱": "水上警察研究所",
    "學位類別": "碩士",
    "畢業學年度": "91",
    "論文出版年": "2003"
  },
  {
    "序號": "31",
    "論文名稱": "我國海巡船艇籌獲管理之研究",
    "研究生": "麥世稚",
    "指導教授": "吳東明",
    "校院名稱": "中央警察大學",
    "系所名稱": "水上警察研究所",
    "學位類別": "碩士",
    "畢業學年度": "92",
    "論文出版年": "2004"
  },
  {
    "序號": "32",
    "論文名稱": "我國海上船舶溢油污染應變作業之改善研究",
    "研究生": "朱振良",
    "指導教授": "楊仲筂　吳東明",
    "校院名稱": "中央警察大學",
    "系所名稱": "水上警察研究所",
    "學位類別": "碩士",
    "畢業學年度": "92",
    "論文出版年": "2004"
  },
  {
    "序號": "33",
    "論文名稱": "IMO統合安全評估系統於海運安全之研究",
    "研究生": "蔡維倫",
    "指導教授": "吳東明",
    "校院名稱": "中央警察大學",
    "系所名稱": "水上警察研究所",
    "學位類別": "碩士",
    "畢業學年度": "92",
    "論文出版年": "2005"
  },
  {
    "序號": "34",
    "論文名稱": "應用平衡計分卡觀點於海岸巡防機關績效管理之研究",
    "研究生": "陳永昌",
    "指導教授": "朱金池　吳東明",
    "校院名稱": "中央警察大學",
    "系所名稱": "水上警察研究所",
    "學位類別": "碩士",
    "畢業學年度": "92",
    "論文出版年": "2004"
  },
  {
    "序號": "35",
    "論文名稱": "海巡執法人員航技職能分析與教育藍圖規畫之研究",
    "研究生": "石介璋",
    "指導教授": "廖坤靜　吳東明",
    "校院名稱": "中央警察大學",
    "系所名稱": "水上警察研究所",
    "學位類別": "碩士",
    "畢業學年度": "92",
    "論文出版年": "2004"
  },
  {
    "序號": "36",
    "論文名稱": "我國海巡機關大型船艦航技訓練與自行發證可行性之研究",
    "研究生": "陳華福",
    "指導教授": "陳佳德　吳東明",
    "校院名稱": "中央警察大學",
    "系所名稱": "水上警察研究所",
    "學位類別": "碩士",
    "畢業學年度": "92",
    "論文出版年": "2004"
  },
  {
    "序號": "37",
    "論文名稱": "水上警察研究所",
    "研究生": "簡日成",
    "指導教授": "吳東明",
    "校院名稱": "中央警察大學",
    "系所名稱": "刑事警察研究所",
    "學位類別": "碩士",
    "畢業學年度": "92",
    "論文出版年": "2003"
  },
  {
    "序號": "38",
    "論文名稱": "論公海犯罪及其防制－以海盜與海上國際恐怖行為為中心",
    "研究生": "扶大桂",
    "指導教授": "魏靜芬",
    "校院名稱": "中央警察大學",
    "系所名稱": "水上警察研究所",
    "學位類別": "碩士",
    "畢業學年度": "93",
    "論文出版年": "2005"
  },
  {
    "序號": "39",
    "論文名稱": "我國船舶監控系統應用於海域巡防之研究",
    "研究生": "李毅信",
    "指導教授": "許克勤\n吳東明",
    "校院名稱": "中央警察大學",
    "系所名稱": "水上警察研究所",
    "學位類別": "碩士",
    "畢業學年度": "93",
    "論文出版年": "2005"
  },
  {
    "序號": "40",
    "論文名稱": "我國海巡人員海事專業訓練機制之研究",
    "研究生": "蔡朝卿",
    "指導教授": "陳佳德\n吳東明",
    "校院名稱": "中央警察大學",
    "系所名稱": "水上警察研究所",
    "學位類別": "碩士",
    "畢業學年度": "93",
    "論文出版年": "2005"
  },
  {
    "序號": "41",
    "論文名稱": "我國海巡船艇保修制度規畫之研究",
    "研究生": "廖敏堯",
    "指導教授": "吳東明",
    "校院名稱": "中央警察大學",
    "系所名稱": "水上警察研究所",
    "學位類別": "碩士",
    "畢業學年度": "93",
    "論文出版年": "2005"
  },
  {
    "序號": "42",
    "論文名稱": "強化我國國際港口保安機制之研究",
    "研究生": "蔡宇鎮",
    "指導教授": "吳東明",
    "校院名稱": "中央警察大學",
    "系所名稱": "水上警察研究所",
    "學位類別": "碩士",
    "畢業學年度": "93",
    "論文出版年": "2005"
  },
  {
    "序號": "43",
    "論文名稱": "論海域執法程序－以登臨　檢查　緊追為中心－",
    "研究生": "葉錫忠",
    "指導教授": "魏靜芬",
    "校院名稱": "中央警察大學",
    "系所名稱": "水上警察研究所",
    "學位類別": "碩士",
    "畢業學年度": "93",
    "論文出版年": "2004"
  },
  {
    "序號": "44",
    "論文名稱": "台灣海峽北部流場之研究",
    "研究生": "蕭憲隆",
    "指導教授": "陳先文",
    "校院名稱": "中央警察大學",
    "系所名稱": "水上警察研究所",
    "學位類別": "碩士",
    "畢業學年度": "94",
    "論文出版年": "2006"
  },
  {
    "序號": "45",
    "論文名稱": "海流垂直結構之研究-以臺灣海峽為例",
    "研究生": "黃冠穎",
    "指導教授": "陳先文",
    "校院名稱": "中央警察大學",
    "系所名稱": "水上警察研究所",
    "學位類別": "碩士",
    "畢業學年度": "94",
    "論文出版年": "2006"
  },
  {
    "序號": "46",
    "論文名稱": "強化我國海難救助系統執行效能之策進作為研究",
    "研究生": "黃瑞原",
    "指導教授": "吳東明",
    "校院名稱": "中央警察大學",
    "系所名稱": "水上警察研究所",
    "學位類別": "碩士",
    "畢業學年度": "94",
    "論文出版年": "2006"
  },
  {
    "序號": "47",
    "論文名稱": "我國海岸巡防機關海域犯罪偵防機制之研究",
    "研究生": "黃永璋",
    "指導教授": "蘇漢霖\n吳東明",
    "校院名稱": "中央警察大學",
    "系所名稱": "水上警察研究所",
    "學位類別": "碩士",
    "畢業學年度": "94",
    "論文出版年": "2006"
  },
  {
    "序號": "48",
    "論文名稱": "我國海域渉外船舶碰撞問題研究-以海域執法作業程序為中心",
    "研究生": "陳志偉",
    "指導教授": "吳東明",
    "校院名稱": "中央警察大學",
    "系所名稱": "水上警察研究所",
    "學位類別": "碩士",
    "畢業學年度": "94",
    "論文出版年": "2006"
  },
  {
    "序號": "49",
    "論文名稱": "派出所巡邏勤務效能之研究",
    "研究生": "黃漢冠",
    "指導教授": "許福生",
    "校院名稱": "中央警察大學",
    "系所名稱": "水上警察研究所",
    "學位類別": "碩士",
    "畢業學年度": "95",
    "論文出版年": "2007"
  },
  {
    "序號": "50",
    "論文名稱": "海洋巡防總局人員晉用管道之研究~以評估養成教育取才為重點",
    "研究生": "葉炳佔",
    "指導教授": "陳佳德\n劉春暉",
    "校院名稱": "中央警察大學",
    "系所名稱": "水上警察研究所",
    "學位類別": "碩士",
    "畢業學年度": "95",
    "論文出版年": "2007"
  },
  {
    "序號": "51",
    "論文名稱": "論海難救助與國家責任之研究",
    "研究生": "林原安",
    "指導教授": "魏靜芬",
    "校院名稱": "中央警察大學",
    "系所名稱": "水上警察研究所",
    "學位類別": "碩士",
    "畢業學年度": "95",
    "論文出版年": "2007"
  },
  {
    "序號": "52",
    "論文名稱": "地轉平衡於南海北部之驗證─以2005年5月為例",
    "研究生": "陳奕光",
    "指導教授": "陳先文",
    "校院名稱": "中央警察大學",
    "系所名稱": "水上警察研究所",
    "學位類別": "碩士",
    "畢業學年度": "95",
    "論文出版年": "2007"
  },
  {
    "序號": "53",
    "論文名稱": "論和平時期海洋軍事活動之國際法規制",
    "研究生": "張慧君",
    "指導教授": "魏靜芬",
    "校院名稱": "中央警察大學",
    "系所名稱": "水上警察研究所",
    "學位類別": "碩士",
    "畢業學年度": "95",
    "論文出版年": "2007"
  },
  {
    "序號": "54",
    "論文名稱": "海巡署海洋油污染查緝之強化作為",
    "研究生": "賀華傑",
    "指導教授": "吳東明",
    "校院名稱": "中央警察大學",
    "系所名稱": "水上警察研究所",
    "學位類別": "碩士",
    "畢業學年度": "96",
    "論文出版年": "2008"
  },
  {
    "序號": "55",
    "論文名稱": "論暫定執法線之法律定位與因應作為",
    "研究生": "傅勝群",
    "指導教授": "姜皇池\n陳國勝",
    "校院名稱": "中央警察大學",
    "系所名稱": "水上警察研究所",
    "學位類別": "碩士",
    "畢業學年度": "96",
    "論文出版年": "2008"
  },
  {
    "序號": "56",
    "論文名稱": "海巡執法對漁民海上作業所生損害之賠償問題",
    "研究生": "江姿蓉",
    "指導教授": "黃異\n陳佳德",
    "校院名稱": "中央警察大學",
    "系所名稱": "水上警察研究所",
    "學位類別": "碩士",
    "畢業學年度": "96",
    "論文出版年": "2008"
  },
  {
    "序號": "57",
    "論文名稱": "台灣地區與大陸地區人民關係條例「收容」之正當法律程序",
    "研究生": "陳正揚",
    "指導教授": "姜皇池\n陳國勝",
    "校院名稱": "中央警察大學",
    "系所名稱": "水上警察研究所",
    "學位類別": "碩士",
    "畢業學年度": "96",
    "論文出版年": "2008"
  },
  {
    "序號": "58",
    "論文名稱": "臺日海巡機關維護海上交通秩序之比較與精進作為",
    "研究生": "汪榮榛",
    "指導教授": "吳東明",
    "校院名稱": "中央警察大學",
    "系所名稱": "水上警察研究所",
    "學位類別": "碩士",
    "畢業學年度": "96",
    "論文出版年": "2008"
  },
  {
    "序號": "59",
    "論文名稱": "從國土安全角度探討我國海巡機關定位之研究",
    "研究生": "滕永俊",
    "指導教授": "宋筱元\n陳佳德",
    "校院名稱": "中央警察大學",
    "系所名稱": "水上警察研究所",
    "學位類別": "碩士",
    "畢業學年度": "96",
    "論文出版年": "2008"
  },
  {
    "序號": "60",
    "論文名稱": "兩岸人民關係條例「留置」之合憲性研究",
    "研究生": "陸家昌",
    "指導教授": "姜皇池\n陳國勝",
    "校院名稱": "中央警察大學",
    "系所名稱": "水上警察研究所",
    "學位類別": "碩士",
    "畢業學年度": "96",
    "論文出版年": "2008"
  },
  {
    "序號": "61",
    "論文名稱": "論我國執行遠洋漁業巡護登臨檢查之因應策略－以WCPFC為中心",
    "研究生": "王茂昇",
    "指導教授": "吳東明",
    "校院名稱": "中央警察大學",
    "系所名稱": "水上警察研究所",
    "學位類別": "碩士",
    "畢業學年度": "96",
    "論文出版年": "2008"
  },
  {
    "序號": "62",
    "論文名稱": "提升海岸巡防機關現場處理能力之研究",
    "研究生": "楊朝卿",
    "指導教授": "楊秋和\n劉春暉",
    "校院名稱": "中央警察大學",
    "系所名稱": "水上警察研究所",
    "學位類別": "碩士",
    "畢業學年度": "96",
    "論文出版年": "2008"
  },
  {
    "序號": "63",
    "論文名稱": "在國土安全概念下之我國港口保安機制規劃-以台中國際商港為例",
    "研究生": "洪文泉",
    "指導教授": "吳東明",
    "校院名稱": "中央警察大學",
    "系所名稱": "水上警察研究所",
    "學位類別": "碩士",
    "畢業學年度": "96",
    "論文出版年": "2008"
  },
  {
    "序號": "64",
    "論文名稱": "從「海洋污染防治標準作業流程」論海巡署執行海洋污染查核機制之研究",
    "研究生": "蔡孟坤",
    "指導教授": "邱文彥\n陳佳德",
    "校院名稱": "中央警察大學",
    "系所名稱": "水上警察研究所",
    "學位類別": "碩士",
    "畢業學年度": "96",
    "論文出版年": "2008"
  },
  {
    "序號": "65",
    "論文名稱": "應用船載式ADCP探討基隆嶼鄰近流場-以2007年夏季為例",
    "研究生": "黃美慈",
    "指導教授": "陳先文",
    "校院名稱": "中央警察大學",
    "系所名稱": "水上警察研究所",
    "學位類別": "碩士",
    "畢業學年度": "96",
    "論文出版年": "2008"
  },
  {
    "序號": "66",
    "論文名稱": "海岸巡防機關納入國防軍事作戰體系之研究-----以我國海岸巡防署組織法第廿四條為中心",
    "研究生": "白正暉",
    "指導教授": "陳佳德\n黃異",
    "校院名稱": "中央警察大學",
    "系所名稱": "水上警察研究所",
    "學位類別": "碩士",
    "畢業學年度": "96",
    "論文出版年": "2008"
  },
  {
    "序號": "67",
    "論文名稱": "海岸巡防機關執行沿近海漁業資源維護之研究",
    "研究生": "黃逸民",
    "指導教授": "吳東明",
    "校院名稱": "中央警察大學",
    "系所名稱": "水上警察研究所",
    "學位類別": "碩士",
    "畢業學年度": "96",
    "論文出版年": "2008"
  },
  {
    "序號": "68",
    "論文名稱": "論公海漁船登檢制度-以我國參與WCPFC之公海漁船登檢為探討重心",
    "研究生": "郭世杰",
    "指導教授": "姜皇池\n陳國勝",
    "校院名稱": "中央警察大學",
    "系所名稱": "水上警察研究所",
    "學位類別": "碩士",
    "畢業學年度": "96",
    "論文出版年": "2008"
  },
  {
    "序號": "69",
    "論文名稱": "論臺日專屬經濟重疊水域漁業爭端之國家責任研究-以暫定執法線為中心",
    "研究生": "邱心怡",
    "指導教授": "姜皇池\n陳國勝",
    "校院名稱": "中央警察大學",
    "系所名稱": "水上警察研究所",
    "學位類別": "碩士",
    "畢業學年度": "97",
    "論文出版年": "2009"
  },
  {
    "序號": "70",
    "論文名稱": "海巡機關在FAO港口國管制措施中定位之研究-以打擊IUU漁船為探討中心",
    "研究生": "黃漢松",
    "指導教授": "姜皇池\n陳國勝",
    "校院名稱": "中央警察大學",
    "系所名稱": "水上警察研究所",
    "學位類別": "碩士",
    "畢業學年度": "97",
    "論文出版年": "2009"
  },
  {
    "序號": "71",
    "論文名稱": "防止船舶污染海洋環境執法之研究－以美國為借鏡",
    "研究生": "李景琪",
    "指導教授": "陳國勝",
    "校院名稱": "中央警察大學",
    "系所名稱": "水上警察研究所",
    "學位類別": "碩士",
    "畢業學年度": "97",
    "論文出版年": "2009"
  },
  {
    "序號": "72",
    "論文名稱": "台灣海峽夏季流量之估算",
    "研究生": "彭宥淋",
    "指導教授": "陳先文",
    "校院名稱": "中央警察大學",
    "系所名稱": "水上警察研究所",
    "學位類別": "碩士",
    "畢業學年度": "97",
    "論文出版年": "2009"
  },
  {
    "序號": "73",
    "論文名稱": "臺灣地區執行港口國管制法制之研究－以基隆港為例",
    "研究生": "曾明羲",
    "指導教授": "吳東明",
    "校院名稱": "中央警察大學",
    "系所名稱": "水上警察研究所",
    "學位類別": "碩士",
    "畢業學年度": "97",
    "論文出版年": "2009"
  },
  {
    "序號": "74",
    "論文名稱": "我國海巡艦艇維修管理面向之研究",
    "研究生": "蔡博豪",
    "指導教授": "吳東明",
    "校院名稱": "中央警察大學",
    "系所名稱": "水上警察研究所",
    "學位類別": "碩士",
    "畢業學年度": "97",
    "論文出版年": "2009"
  },
  {
    "序號": "75",
    "論文名稱": "海巡人員槍械使用認證之探討",
    "研究生": "黃介政",
    "指導教授": "陳國勝\n陳佳德",
    "校院名稱": "中央警察大學",
    "系所名稱": "水上警察研究所",
    "學位類別": "碩士",
    "畢業學年度": "97",
    "論文出版年": "2009"
  },
  {
    "序號": "76",
    "論文名稱": "海岸巡防署500噸級水噴射推進系統巡防艦籌建過程之探析-以金門巡防艦為例",
    "研究生": "黃國安",
    "指導教授": "吳東明",
    "校院名稱": "中央警察大學",
    "系所名稱": "水上警察研究所",
    "學位類別": "碩士",
    "畢業學年度": "97",
    "論文出版年": "2009"
  },
  {
    "序號": "77",
    "論文名稱": "海岸巡防機關於海岸地區行政檢查之研究",
    "研究生": "張嘉宇",
    "指導教授": "姜皇池\n陳國勝",
    "校院名稱": "中央警察大學",
    "系所名稱": "水上警察研究所",
    "學位類別": "碩士",
    "畢業學年度": "97",
    "論文出版年": "2009"
  },
  {
    "序號": "78",
    "論文名稱": "呂宋海峽表面流場之初步探討",
    "研究生": "蘇登發",
    "指導教授": "陳先文",
    "校院名稱": "中央警察大學",
    "系所名稱": "水上警察研究所",
    "學位類別": "碩士",
    "畢業學年度": "97",
    "論文出版年": "2009"
  },
  {
    "序號": "79",
    "論文名稱": "未來海巡機關人事制度變革之研究",
    "研究生": "謝添進",
    "指導教授": "吳東明",
    "校院名稱": "中央警察大學",
    "系所名稱": "水上警察研究所",
    "學位類別": "碩士",
    "畢業學年度": "98",
    "論文出版年": "2010"
  },
  {
    "序號": "80",
    "論文名稱": "我國海巡空偵任務之研究－無人空中載具之運用",
    "研究生": "周泰祺",
    "指導教授": "吳東明",
    "校院名稱": "中央警察大學",
    "系所名稱": "水上警察研究所",
    "學位類別": "碩士",
    "畢業學年度": "98",
    "論文出版年": "2010"
  },
  {
    "序號": "81",
    "論文名稱": "論外國船舶無害通過執行管轄之劃分--以中華民國領海及鄰接區法第17條為探討核心",
    "研究生": "周志昌",
    "指導教授": "陳國勝",
    "校院名稱": "中央警察大學",
    "系所名稱": "水上警察研究所",
    "學位類別": "碩士",
    "畢業學年度": "98",
    "論文出版年": "2010"
  },
  {
    "序號": "82",
    "論文名稱": "「論公海非船旗國管轄之發展」－以漁業養護與管理為探討核心",
    "研究生": "陳奎瑾",
    "指導教授": "姜皇池\n陳國勝",
    "校院名稱": "中央警察大學",
    "系所名稱": "水上警察研究所",
    "學位類別": "碩士",
    "畢業學年度": "98",
    "論文出版年": "2010"
  },
  {
    "序號": "83",
    "論文名稱": "海上登檢制度及其訓練之研究—我國與美國之分析比較",
    "研究生": "洪政儀",
    "指導教授": "姜皇池",
    "校院名稱": "中央警察大學",
    "系所名稱": "水上警察研究所",
    "學位類別": "碩士",
    "畢業學年度": "98",
    "論文出版年": "2010"
  },
  {
    "序號": "84",
    "論文名稱": "我國海難救助體系的回顧檢討及前瞻規劃—以海岸巡防署為中心",
    "研究生": "賴宜琳",
    "指導教授": "吳東明",
    "校院名稱": "中央警察大學",
    "系所名稱": "水上警察研究所",
    "學位類別": "碩士",
    "畢業學年度": "98",
    "論文出版年": "2010"
  },
  {
    "序號": "85",
    "論文名稱": "台灣海峽北部流場及水文場之時空變化",
    "研究生": "吳幸芬",
    "指導教授": "陳先文",
    "校院名稱": "中央警察大學",
    "系所名稱": "水上警察研究所",
    "學位類別": "碩士",
    "畢業學年度": "98",
    "論文出版年": "2010"
  },
  {
    "序號": "86",
    "論文名稱": "海巡署新造1000噸級巡護船振動及噪音舒適度研究",
    "研究生": "邱博文",
    "指導教授": "劉春暉",
    "校院名稱": "中央警察大學",
    "系所名稱": "水上警察研究所",
    "學位類別": "碩士",
    "畢業學年度": "99",
    "論文出版年": "2011"
  },
  {
    "序號": "87",
    "論文名稱": "海域執法中之國家管轄權競合-以台日間衝突案例為研究核心",
    "研究生": "葉力君",
    "指導教授": "姜皇池　陳佳德",
    "校院名稱": "中央警察大學",
    "系所名稱": "水上警察研究所",
    "學位類別": "碩士",
    "畢業學年度": "99",
    "論文出版年": "2011"
  },
  {
    "序號": "88",
    "論文名稱": "我國對海盜行為之法制問題研究－以日本《海盜行為處罰暨海盜因應法》為參考",
    "研究生": "施凡勤",
    "指導教授": "李明峻　陳佳德",
    "校院名稱": "中央警察大學",
    "系所名稱": "水上警察研究所",
    "學位類別": "碩士",
    "畢業學年度": "99",
    "論文出版年": "2011"
  },
  {
    "序號": "89",
    "論文名稱": "水上摩托車管理制度之研究",
    "研究生": "王晟瀚",
    "指導教授": "周文生　劉春暉",
    "校院名稱": "中央警察大學",
    "系所名稱": "水上警察研究所",
    "學位類別": "碩士",
    "畢業學年度": "99",
    "論文出版年": "2011"
  },
  {
    "序號": "90",
    "論文名稱": "海巡機關執行海洋觀測之SWOT分析",
    "研究生": "黃恒鈞",
    "指導教授": "陳先文",
    "校院名稱": "中央警察大學",
    "系所名稱": "水上警察研究所",
    "學位類別": "碩士",
    "畢業學年度": "99",
    "論文出版年": "2011"
  },
  {
    "序號": "91",
    "論文名稱": "海流浮標應用在海上搜救之研究-以台灣東部海域為例",
    "研究生": "楊智惟",
    "指導教授": "陳先文",
    "校院名稱": "中央警察大學",
    "系所名稱": "水上警察研究所",
    "學位類別": "碩士",
    "畢業學年度": "99",
    "論文出版年": "2011"
  },
  {
    "序號": "92",
    "論文名稱": "海岸巡防機關執行娛樂漁業管理之研究",
    "研究生": "張致遠",
    "指導教授": "姜皇池　陳國勝",
    "校院名稱": "中央警察大學",
    "系所名稱": "水上警察研究所",
    "學位類別": "碩士",
    "畢業學年度": "99",
    "論文出版年": "2011"
  },
  {
    "序號": "93",
    "論文名稱": "「精進海域巡防能量之船艦寬頻通信系統研究」—以海巡署衛星船位回報系統為例",
    "研究生": "沈啟仁",
    "指導教授": "吳東明",
    "校院名稱": "中央警察大學",
    "系所名稱": "水上警察研究所",
    "學位類別": "碩士",
    "畢業學年度": "99",
    "論文出版年": "2011"
  },
  {
    "序號": "94",
    "論文名稱": "臺灣東北部海域垂直混合現象之探討",
    "研究生": "周豐成",
    "指導教授": "陳先文",
    "校院名稱": "中央警察大學",
    "系所名稱": "水上警察研究所",
    "學位類別": "碩士",
    "畢業學年度": "99",
    "論文出版年": "2011"
  },
  {
    "序號": "95",
    "論文名稱": "應用主成份分析與群集分析於水文資料之比較研究-以台灣鄰近海域為例",
    "研究生": "林谷銘",
    "指導教授": "陳先文",
    "校院名稱": "中央警察大學",
    "系所名稱": "水上警察研究所",
    "學位類別": "碩士",
    "畢業學年度": "99",
    "論文出版年": "2010"
  },
  {
    "序號": "96",
    "論文名稱": "AHP層級分析法應用於無線網路資訊系統評選方案之研究-以海巡署艦艇為例",
    "研究生": "陳建崧",
    "指導教授": "劉春暉",
    "校院名稱": "中央警察大學",
    "系所名稱": "水上警察研究所",
    "學位類別": "碩士",
    "畢業學年度": "99",
    "論文出版年": "2010"
  },
  {
    "序號": "97",
    "論文名稱": "海事安全之檢討與對策探析—以歐盟案例為借鏡",
    "研究生": "許智傑",
    "指導教授": "吳東明",
    "校院名稱": "中央警察大學",
    "系所名稱": "水上警察研究所",
    "學位類別": "碩士",
    "畢業學年度": "99",
    "論文出版年": "2010"
  },
  {
    "序號": "98",
    "論文名稱": "標準化海巡機關核心職能之研究-以探討所需之師資　設備　課程為中心",
    "研究生": "李裕智",
    "指導教授": "姜皇池\n陳國勝",
    "校院名稱": "中央警察大學",
    "系所名稱": "水上警察研究所",
    "學位類別": "碩士",
    "畢業學年度": "100",
    "論文出版年": "2012"
  },
  {
    "序號": "99",
    "論文名稱": "海巡署遠洋漁業巡護執勤能量之研究-以新建一千噸級巡護七號船為例",
    "研究生": "蔡勝利",
    "指導教授": "吳東明",
    "校院名稱": "中央警察大學",
    "系所名稱": "水上警察研究所",
    "學位類別": "碩士",
    "畢業學年度": "100",
    "論文出版年": "2011"
  },
  {
    "序號": "100",
    "論文名稱": "小三通後金門海域大陸船舶違法行為態樣之研究",
    "研究生": "鍾宗福",
    "指導教授": "吳東明",
    "校院名稱": "中央警察大學",
    "系所名稱": "水上警察研究所",
    "學位類別": "碩士",
    "畢業學年度": "100",
    "論文出版年": "2011"
  },
  {
    "序號": "101",
    "論文名稱": "我國海巡船艇維保管理制度之研究",
    "研究生": "陳進益",
    "指導教授": "吳東明",
    "校院名稱": "中央警察大學",
    "系所名稱": "水上警察研究所",
    "學位類別": "碩士",
    "畢業學年度": "100",
    "論文出版年": "2011"
  },
  {
    "序號": "102",
    "論文名稱": "建置適用於我國海巡機關任務之海洋資料庫芻議",
    "研究生": "盧主斌",
    "指導教授": "陳先文",
    "校院名稱": "中央警察大學",
    "系所名稱": "水上警察研究所",
    "學位類別": "碩士",
    "畢業學年度": "100",
    "論文出版年": "2012"
  },
  {
    "序號": "103",
    "論文名稱": "海巡署大型船艦維修效率及品質精進策略之研究",
    "研究生": "徐祥航",
    "指導教授": "劉春暉",
    "校院名稱": "中央警察大學",
    "系所名稱": "水上警察研究所",
    "學位類別": "碩士",
    "畢業學年度": "100",
    "論文出版年": "2012"
  },
  {
    "序號": "104",
    "論文名稱": "海岸巡防機關執行管轄作為─兩岸海域執法合作之必要性檢視",
    "研究生": "廖雲宏",
    "指導教授": "姜皇池　陳國勝",
    "校院名稱": "中央警察大學",
    "系所名稱": "水上警察研究所",
    "學位類別": "碩士",
    "畢業學年度": "100",
    "論文出版年": "2012"
  },
  {
    "序號": "105",
    "論文名稱": "論海域執法機關司法警察職權之分配",
    "研究生": "歐玉飛",
    "指導教授": "姜皇池\n陳國勝",
    "校院名稱": "中央警察大學",
    "系所名稱": "水上警察研究所",
    "學位類別": "碩士",
    "畢業學年度": "100",
    "論文出版年": "2012"
  },
  {
    "序號": "106",
    "論文名稱": "海岸巡防署船舶自動識別系統之比較分析及應用研究",
    "研究生": "廖偉辰",
    "指導教授": "劉春暉",
    "校院名稱": "中央警察大學",
    "系所名稱": "水上警察研究所",
    "學位類別": "碩士",
    "畢業學年度": "100",
    "論文出版年": "2012"
  },
  {
    "序號": "107",
    "論文名稱": "海巡執法與兩岸人民關係條例留置規定之探討-以人權保障法理為核心",
    "研究生": "黃信源",
    "指導教授": "李明峻　陳先文",
    "校院名稱": "中央警察大學",
    "系所名稱": "水上警察研究所",
    "學位類別": "碩士",
    "畢業學年度": "101",
    "論文出版年": "2013"
  },
  {
    "序號": "108",
    "論文名稱": "我國現行海難救助體系之檢討－以美　日　中等國立法及實務運作為借鏡",
    "研究生": "李子嘉",
    "指導教授": "李明峻　陳佳德",
    "校院名稱": "中央警察大學",
    "系所名稱": "水上警察研究所",
    "學位類別": "碩士",
    "畢業學年度": "101",
    "論文出版年": "2013"
  },
  {
    "序號": "109",
    "論文名稱": "海巡人員航技職能之前瞻規劃研究-以強化海勤人力資源為目標",
    "研究生": "何烜丞",
    "指導教授": "吳東明",
    "校院名稱": "中央警察大學",
    "系所名稱": "水上警察研究所",
    "學位類別": "碩士",
    "畢業學年度": "101",
    "論文出版年": "2013"
  },
  {
    "序號": "110",
    "論文名稱": "論臺灣管轄海域海上駁油之適法性探討",
    "研究生": "黃哲雍",
    "指導教授": "陳佳德　姜皇池",
    "校院名稱": "中央警察大學",
    "系所名稱": "水上警察研究所",
    "學位類別": "碩士",
    "畢業學年度": "101",
    "論文出版年": "1020"
  },
  {
    "序號": "111",
    "論文名稱": "中國大陸海軍護航我國籍漁船之對策研究-以防止索馬利亞海域海盜劫持案件為例",
    "研究生": "曾明斌",
    "指導教授": "吳東明",
    "校院名稱": "中央警察大學",
    "系所名稱": "水上警察研究所",
    "學位類別": "碩士",
    "畢業學年度": "101",
    "論文出版年": "2013"
  },
  {
    "序號": "112",
    "論文名稱": "海上緊急救護系統建構之研究-以「新德益168號漁船後送案」為例",
    "研究生": "呂俊寬",
    "指導教授": "吳東明",
    "校院名稱": "中央警察大學",
    "系所名稱": "水上警察研究所",
    "學位類別": "碩士",
    "畢業學年度": "101",
    "論文出版年": "2013"
  },
  {
    "序號": "113",
    "論文名稱": "海巡艦艇維修管理制度研究-以履約爭議為中心",
    "研究生": "吳孟哲",
    "指導教授": "吳東明",
    "校院名稱": "中央警察大學",
    "系所名稱": "水上警察研究所",
    "學位類別": "碩士",
    "畢業學年度": "101",
    "論文出版年": "2013"
  },
  {
    "序號": "114",
    "論文名稱": "涉外船舶碰撞事故調查與海事科技取證之研究",
    "研究生": "陳致延",
    "指導教授": "吳東明",
    "校院名稱": "中央警察大學",
    "系所名稱": "水上警察研究所",
    "學位類別": "碩士",
    "畢業學年度": "101",
    "論文出版年": "2013"
  },
  {
    "序號": "115",
    "論文名稱": "事故現場指揮體系研究-海上災害事故之應用",
    "研究生": "余卓縉",
    "指導教授": "吳東明",
    "校院名稱": "中央警察大學",
    "系所名稱": "水上警察研究所",
    "學位類別": "碩士",
    "畢業學年度": "101",
    "論文出版年": "2013"
  },
  {
    "序號": "116",
    "論文名稱": "海岸巡防署大型艦勤務規劃研析-以偉星巡防艦為例",
    "研究生": "鍾容軒",
    "指導教授": "吳東明",
    "校院名稱": "中央警察大學",
    "系所名稱": "水上警察研究所",
    "學位類別": "碩士",
    "畢業學年度": "101",
    "論文出版年": "2013"
  },
  {
    "序號": "117",
    "論文名稱": "海巡艦艇人力職務設計之研究",
    "研究生": "劉賢國",
    "指導教授": "姜皇池　陳國勝",
    "校院名稱": "中央警察大學",
    "系所名稱": "水上警察研究所",
    "學位類別": "碩士",
    "畢業學年度": "102",
    "論文出版年": "2014"
  },
  {
    "序號": "118",
    "論文名稱": "從美日海上執法機關探討我國海巡署人事任用與培訓制度",
    "研究生": "梁曉年",
    "指導教授": "姜皇池　陳國勝",
    "校院名稱": "中央警察大學",
    "系所名稱": "水上警察研究所",
    "學位類別": "碩士",
    "畢業學年度": "102",
    "論文出版年": "2014"
  },
  {
    "序號": "119",
    "論文名稱": "我國因應《STCW-F公約》之研究",
    "研究生": "莊惟守",
    "指導教授": "姜皇池　陳國勝",
    "校院名稱": "中央警察大學",
    "系所名稱": "水上警察研究所",
    "學位類別": "碩士",
    "畢業學年度": "102",
    "論文出版年": "2014"
  },
  {
    "序號": "120",
    "論文名稱": "論我國海洋保護區整合管理之研究:法制觀點",
    "研究生": "高規肯",
    "指導教授": "邱文彥　陳佳德",
    "校院名稱": "中央警察大學",
    "系所名稱": "水上警察研究所",
    "學位類別": "碩士",
    "畢業學年度": "102",
    "論文出版年": "2014"
  },
  {
    "序號": "121",
    "論文名稱": "我國海上救護審核機制及派勤能量之研究-以「漁船船員海上傷病申請救援通訊諮詢機制」為中心",
    "研究生": "藍侑書",
    "指導教授": "姜皇池　陳佳德",
    "校院名稱": "中央警察大學",
    "系所名稱": "水上警察研究所",
    "學位類別": "碩士",
    "畢業學年度": "102",
    "論文出版年": "2014"
  },
  {
    "序號": "122",
    "論文名稱": "從文武關係理論論我國海巡人員一元化之研究",
    "研究生": "梁乃文",
    "指導教授": "陳國勝　姜皇池",
    "校院名稱": "中央警察大學",
    "系所名稱": "水上警察研究所",
    "學位類別": "碩士",
    "畢業學年度": "102",
    "論文出版年": "2014"
  },
  {
    "序號": "123",
    "論文名稱": "海洋油污染處理新方法-奈米光觸媒於重油的分解",
    "研究生": "莊昆霖",
    "指導教授": "林沐謙",
    "校院名稱": "中央警察大學",
    "系所名稱": "水上警察研究所",
    "學位類別": "碩士",
    "畢業學年度": "102",
    "論文出版年": "2014"
  },
  {
    "序號": "124",
    "論文名稱": "奈米光觸媒在海洋油污染之應用-以柴油油污染處理為例",
    "研究生": "郭崇裕",
    "指導教授": "林沐謙",
    "校院名稱": "中央警察大學",
    "系所名稱": "水上警察研究所",
    "學位類別": "碩士",
    "畢業學年度": "102",
    "論文出版年": "2014"
  },
  {
    "序號": "125",
    "論文名稱": "海洋油污染防治新技術-奈米技術在輕油分解的應用",
    "研究生": "陳建有",
    "指導教授": "林沐謙",
    "校院名稱": "中央警察大學",
    "系所名稱": "水上警察研究所",
    "學位類別": "碩士",
    "畢業學年度": "102",
    "論文出版年": "2014"
  },
  {
    "序號": "126",
    "論文名稱": "我國海域(岸)執法人員教育訓練議題與設施探討-以教育訓練中心為例",
    "研究生": "李孝勇",
    "指導教授": "吳東明",
    "校院名稱": "中央警察大學",
    "系所名稱": "水上警察研究所",
    "學位類別": "碩士",
    "畢業學年度": "103",
    "論文出版年": "2015"
  },
  {
    "序號": "127",
    "論文名稱": "海上入出國管轄權之研究-以鄰接區移民管轄為核心",
    "研究生": "王亭絜",
    "指導教授": "陳佳德　姜皇池",
    "校院名稱": "中央警察大學",
    "系所名稱": "水上警察研究所",
    "學位類別": "碩士",
    "畢業學年度": "103",
    "論文出版年": "2015"
  },
  {
    "序號": "128",
    "論文名稱": "高效率海洋油污染處理法理論與實例之研究",
    "研究生": "黃書彥",
    "指導教授": "林沐謙",
    "校院名稱": "中央警察大學",
    "系所名稱": "水上警察研究所",
    "學位類別": "碩士",
    "畢業學年度": "103",
    "論文出版年": "2015"
  },
  {
    "序號": "129",
    "論文名稱": "我國海事案件處理與海難救助對策之研究─以海巡署案例為中心",
    "研究生": "許建忠",
    "指導教授": "吳東明",
    "校院名稱": "中央警察大學",
    "系所名稱": "水上警察研究所",
    "學位類別": "碩士",
    "畢業學年度": "103",
    "論文出版年": "2015"
  },
  {
    "序號": "130",
    "論文名稱": "台灣處理中國漁船越界捕魚對策之研究",
    "研究生": "宿里和齊",
    "指導教授": "姜皇池　劉春暉",
    "校院名稱": "中央警察大學",
    "系所名稱": "水上警察研究所",
    "學位類別": "碩士",
    "畢業學年度": "103",
    "論文出版年": "2015"
  },
  {
    "序號": "131",
    "論文名稱": "論我國海巡機關自行發證後海勤人力培育-以海上保安廳為借鏡",
    "研究生": "郭昱辰",
    "指導教授": "陳佳德　姜皇池",
    "校院名稱": "中央警察大學",
    "系所名稱": "水上警察研究所",
    "學位類別": "碩士",
    "畢業學年度": "103",
    "論文出版年": "2015"
  },
  {
    "序號": "132",
    "論文名稱": "海巡人力資源發展的教育訓練規劃-以專業軍官班為例",
    "研究生": "林智明",
    "指導教授": "吳東明",
    "校院名稱": "中央警察大學",
    "系所名稱": "水上警察研究所",
    "學位類別": "碩士",
    "畢業學年度": "103",
    "論文出版年": "2015"
  },
  {
    "序號": "133",
    "論文名稱": "我國海巡機關中西太平洋巡護之研究-以登臨及檢查為中心-",
    "研究生": "粘國忠",
    "指導教授": "林廷輝\n陳佳德",
    "校院名稱": "中央警察大學",
    "系所名稱": "水上警察研究所",
    "學位類別": "碩士",
    "畢業學年度": "104",
    "論文出版年": "2016"
  },
  {
    "序號": "134",
    "論文名稱": "海巡機關取締越界大陸漁船後續執行之研究",
    "研究生": "張群和",
    "指導教授": "陳佳德\n林廷輝",
    "校院名稱": "中央警察大學",
    "系所名稱": "水上警察研究所",
    "學位類別": "碩士",
    "畢業學年度": "104",
    "論文出版年": "2016"
  },
  {
    "序號": "135",
    "論文名稱": "台灣海峽西北部表面流場之探究-以2012年5至6月為例",
    "研究生": "陳威安",
    "指導教授": "陳先文",
    "校院名稱": "中央警察大學",
    "系所名稱": "水上警察研究所",
    "學位類別": "碩士",
    "畢業學年度": "104",
    "論文出版年": "2016"
  },
  {
    "序號": "136",
    "論文名稱": "我國國際商港安全管制機關之研究-以美國日本為例",
    "研究生": "張世宏",
    "指導教授": "姜皇池\n劉春暉",
    "校院名稱": "中央警察大學",
    "系所名稱": "水上警察研究所",
    "學位類別": "碩士",
    "畢業學年度": "104",
    "論文出版年": "2016"
  },
  {
    "序號": "137",
    "論文名稱": "由海水位變化推估台灣海峽流量之研究",
    "研究生": "李懿哲",
    "指導教授": "陳先文",
    "校院名稱": "中央警察大學",
    "系所名稱": "水上警察研究所",
    "學位類別": "碩士",
    "畢業學年度": "104",
    "論文出版年": "2016"
  },
  {
    "序號": "138",
    "論文名稱": "海洋油污染鑑定-化學指紋逆向追蹤調查",
    "研究生": "陳韋睿",
    "指導教授": "張啟隱\n林沐謙",
    "校院名稱": "中央警察大學",
    "系所名稱": "水上警察研究所",
    "學位類別": "碩士",
    "畢業學年度": "104",
    "論文出版年": "2016"
  },
  {
    "序號": "139",
    "論文名稱": "海巡機關海勤人力培訓之研究-以模擬機訓練和實船訓練為探討中心",
    "研究生": "陳立喬",
    "指導教授": "劉春暉",
    "校院名稱": "中央警察大學",
    "系所名稱": "水上警察研究所",
    "學位類別": "碩士",
    "畢業學年度": "104",
    "論文出版年": "2016"
  },
  {
    "序號": "140",
    "論文名稱": "大陸地區人民強制出境暨收容與人權保障研究",
    "研究生": "劉全原",
    "指導教授": "蔡庭榕\n劉春暉",
    "校院名稱": "中央警察大學",
    "系所名稱": "水上警察研究所",
    "學位類別": "碩士",
    "畢業學年度": "104",
    "論文出版年": "2016"
  },
  {
    "序號": "141",
    "論文名稱": "論太平島之法律地位─以南海仲裁案為核心",
    "研究生": "賴建志",
    "指導教授": "姜皇池　陳國勝",
    "校院名稱": "中央警察大學",
    "系所名稱": "水上警察研究所",
    "學位類別": "碩士",
    "畢業學年度": "105",
    "論文出版年": "2017"
  },
  {
    "序號": "142",
    "論文名稱": "我國海巡人員海上犯罪檢查搜索之探討",
    "研究生": "黃琮煥",
    "指導教授": "吳東明",
    "校院名稱": "中央警察大學",
    "系所名稱": "水上警察研究所",
    "學位類別": "碩士",
    "畢業學年度": "105",
    "論文出版年": "2017"
  },
  {
    "序號": "143",
    "論文名稱": "海巡機關編制教官核心職能之探討-以專業軍官班課程設計為例",
    "研究生": "邱瑞讀",
    "指導教授": "吳東明",
    "校院名稱": "中央警察大學",
    "系所名稱": "水上警察研究所",
    "學位類別": "碩士",
    "畢業學年度": "105",
    "論文出版年": "2016"
  },
  {
    "序號": "144",
    "論文名稱": "未來我國海巡署的海勤人力資源規劃之研究",
    "研究生": "賴冠丞",
    "指導教授": "吳東明",
    "校院名稱": "中央警察大學",
    "系所名稱": "水上警察研究所",
    "學位類別": "碩士",
    "畢業學年度": "105",
    "論文出版年": "2017"
  },
  {
    "序號": "145",
    "論文名稱": "我國集會遊行修法之研究-以海上集會遊行為核心",
    "研究生": "宋良桂",
    "指導教授": "陳佳德　姜皇池",
    "校院名稱": "中央警察大學",
    "系所名稱": "水上警察研究所",
    "學位類別": "碩士",
    "畢業學年度": "105",
    "論文出版年": "2016"
  },
  {
    "序號": "146",
    "論文名稱": "海域執法與國家賠償責任之研究-以海巡人員個人責任為重點",
    "研究生": "黃明輝",
    "指導教授": "姜皇池　劉春暉",
    "校院名稱": "中央警察大學",
    "系所名稱": "水上警察研究所",
    "學位類別": "碩士",
    "畢業學年度": "105",
    "論文出版年": "2016"
  },
  {
    "序號": "147",
    "論文名稱": "論海巡機關平戰轉換制度─與美　日　中制度之比較研究",
    "研究生": "董昀真",
    "指導教授": "姜皇池\n陳國勝",
    "校院名稱": "中央警察大學",
    "系所名稱": "水上警察研究所",
    "學位類別": "碩士",
    "畢業學年度": "106",
    "論文出版年": "2018"
  },
  {
    "序號": "148",
    "論文名稱": "論《海岸巡防法》之特別法地位",
    "研究生": "陳力瑋",
    "指導教授": "姜皇池　陳國勝",
    "校院名稱": "中央警察大學",
    "系所名稱": "水上警察研究所",
    "學位類別": "碩士",
    "畢業學年度": "106",
    "論文出版年": "2018"
  },
  {
    "序號": "149",
    "論文名稱": "我國海岸巡防機關水下救助任務現況與展望",
    "研究生": "詹育仁",
    "指導教授": "林世昌",
    "校院名稱": "中央警察大學",
    "系所名稱": "水上警察研究所",
    "學位類別": "碩士",
    "畢業學年度": "106",
    "論文出版年": "2018"
  },
  {
    "序號": "150",
    "論文名稱": "未來我國海事調查制度的精進作為研析",
    "研究生": "林耕範",
    "指導教授": "吳東明",
    "校院名稱": "中央警察大學",
    "系所名稱": "水上警察研究所",
    "學位類別": "碩士",
    "畢業學年度": "106",
    "論文出版年": "2017"
  },
  {
    "序號": "151",
    "論文名稱": "由國際法論海峽兩岸之司法互助",
    "研究生": "黃水願",
    "指導教授": "原始檔無",
    "校院名稱": "中央警察大學",
    "系所名稱": "水上警察研究所",
    "學位類別": "碩士",
    "畢業學年度": "107",
    "論文出版年": "2019"
  },
  {
    "序號": "152",
    "論文名稱": "海巡人員刑案偵辦技巧與移送作業精進之研究",
    "研究生": "李進安",
    "指導教授": "吳東明",
    "校院名稱": "中央警察大學",
    "系所名稱": "水上警察研究所",
    "學位類別": "碩士",
    "畢業學年度": "107",
    "論文出版年": "2018"
  },
  {
    "序號": "153",
    "論文名稱": "預防船舶擱淺溢油污染風險管理之研究",
    "研究生": "李東閔",
    "指導教授": "林沐謙",
    "校院名稱": "中央警察大學",
    "系所名稱": "水上警察研究所",
    "學位類別": "碩士",
    "畢業學年度": "107",
    "論文出版年": "2019"
  },
  {
    "序號": "154",
    "論文名稱": "海巡機關處理中國大陸船舶在我國海域捕魚行為之探討",
    "研究生": "柯庭葦",
    "指導教授": "姜皇池\n陳國勝",
    "校院名稱": "中央警察大學",
    "系所名稱": "水上警察研究所",
    "學位類別": "碩士",
    "畢業學年度": "107",
    "論文出版年": "2019"
  },
  {
    "序號": "155",
    "論文名稱": "我國海巡機關無人飛行載具之實作案例研究",
    "研究生": "洪肇羲",
    "指導教授": "吳東明",
    "校院名稱": "中央警察大學",
    "系所名稱": "水上警察研究所",
    "學位類別": "碩士",
    "畢業學年度": "107",
    "論文出版年": "2019"
  },
  {
    "序號": "156",
    "論文名稱": "GPS追蹤器應用於犯罪偵查之適法性探討",
    "研究生": "許宏銘",
    "指導教授": "林沐謙",
    "校院名稱": "中央警察大學",
    "系所名稱": "水上警察研究所",
    "學位類別": "碩士",
    "畢業學年度": "107",
    "論文出版年": "2019"
  },
  {
    "序號": "157",
    "論文名稱": "我國海洋治理機關的未來發展研究",
    "研究生": "李承哲",
    "指導教授": "吳東明",
    "校院名稱": "中央警察大學",
    "系所名稱": "水上警察研究所",
    "學位類別": "碩士",
    "畢業學年度": "107",
    "論文出版年": "2019"
  },
  {
    "序號": "158",
    "論文名稱": "海巡機關與漁業主管機關間漁船海事安全管轄權之研究－以日本法制為例",
    "研究生": "周承緯",
    "指導教授": "姜皇池\n劉春暉",
    "校院名稱": "中央警察大學",
    "系所名稱": "水上警察研究所",
    "學位類別": "碩士",
    "畢業學年度": "107",
    "論文出版年": "2019"
  },
  {
    "序號": "159",
    "論文名稱": "臺灣海峽中部流場之初探-以海巡署苗栗艦艦載ADCP之觀測分析為例",
    "研究生": "陳冠任",
    "指導教授": "陳先文",
    "校院名稱": "中央警察大學",
    "系所名稱": "水上警察研究所",
    "學位類別": "碩士",
    "畢業學年度": "107",
    "論文出版年": "2019"
  },
  {
    "序號": "160",
    "論文名稱": "論海岸巡防機關之器械使用",
    "研究生": "陳宥丞",
    "指導教授": "姜皇池,葉雲虎",
    "校院名稱": "中央警察大學",
    "系所名稱": "水上警察研究所",
    "學位類別": "碩士",
    "畢業學年度": "107",
    "論文出版年": "2019"
  },
  {
    "序號": "161",
    "論文名稱": "海巡署大型船艦護漁政策執行研究-以機動海巡隊人員為中心",
    "研究生": "廖紘毅",
    "指導教授": "吳東明",
    "校院名稱": "中央警察大學",
    "系所名稱": "水上警察研究所",
    "學位類別": "碩士",
    "畢業學年度": "107",
    "論文出版年": "2019"
  },
  {
    "序號": "162",
    "論文名稱": "事故指揮體系應用與探討－以「穩鵬號」漁船海上喋血救援案為例",
    "研究生": "陳志欽",
    "指導教授": "林沐謙",
    "校院名稱": "中央警察大學",
    "系所名稱": "水上警察研究所",
    "學位類別": "碩士",
    "畢業學年度": "108",
    "論文出版年": "2020"
  },
  {
    "序號": "163",
    "論文名稱": "「籌建海巡艦艇發展計畫」規劃執行研究-以全壽期管理思維為中心",
    "研究生": "曾俊瑜",
    "指導教授": "吳東明",
    "校院名稱": "中央警察大學",
    "系所名稱": "水上警察研究所",
    "學位類別": "碩士",
    "畢業學年度": "108",
    "論文出版年": "2020"
  },
  {
    "序號": "164",
    "論文名稱": "論中菲南海仲裁案對島嶼法律地位之解釋",
    "研究生": "許嘉倩",
    "指導教授": "劉春暉\n林廷輝",
    "校院名稱": "中央警察大學",
    "系所名稱": "水上警察研究所",
    "學位類別": "碩士",
    "畢業學年度": "108",
    "論文出版年": "2020"
  },
  {
    "序號": "165",
    "論文名稱": "海巡機關民力運用建置之研究",
    "研究生": "鄭雅尹",
    "指導教授": "姜皇池\n劉春暉",
    "校院名稱": "中央警察大學",
    "系所名稱": "水上警察研究所",
    "學位類別": "碩士",
    "畢業學年度": "108",
    "論文出版年": "2020"
  },
  {
    "序號": "166",
    "論文名稱": "我國未來海洋治理規劃—以國際海洋生物多樣性的永續發展為中心",
    "研究生": "劉建廷",
    "指導教授": "吳東明",
    "校院名稱": "中央警察大學",
    "系所名稱": "水上警察研究所",
    "學位類別": "碩士",
    "畢業學年度": "108",
    "論文出版年": "2020"
  },
  {
    "序號": "167",
    "論文名稱": "我國海上犯罪偵防的應用策略研析—以無人空中載具為中心",
    "研究生": "莊佳智",
    "指導教授": "吳東明",
    "校院名稱": "中央警察大學",
    "系所名稱": "水上警察研究所",
    "學位類別": "碩士",
    "畢業學年度": "108",
    "論文出版年": "2020"
  },
  {
    "序號": "168",
    "論文名稱": "應用浮球漂流資料分析冬季台灣海峽北部表層流場-以2017年為例",
    "研究生": "曾廷嘉",
    "指導教授": "陳先文",
    "校院名稱": "中央警察大學",
    "系所名稱": "水上警察研究所",
    "學位類別": "碩士",
    "畢業學年度": "108",
    "論文出版年": "2020"
  },
  {
    "序號": "169",
    "論文名稱": "我國海洋主管機關的法制與執行規劃-以離岸風能產業為中心",
    "研究生": "葉才郁",
    "指導教授": "吳東明",
    "校院名稱": "中央警察大學",
    "系所名稱": "水上警察研究所",
    "學位類別": "碩士",
    "畢業學年度": "108",
    "論文出版年": "2020"
  },
  {
    "序號": "170",
    "論文名稱": "論太平島海域劃設海洋保護區之可行性-以解決南海爭端為目的",
    "研究生": "張家翰",
    "指導教授": "姜皇池\n葉雲虎",
    "校院名稱": "中央警察大學",
    "系所名稱": "水上警察研究所",
    "學位類別": "碩士",
    "畢業學年度": "108",
    "論文出版年": "2020"
  },
  {
    "序號": "171",
    "論文名稱": "論非法入出國(境)法制-以海上偷渡犯罪為核心",
    "研究生": "李委峻",
    "指導教授": "姜皇池\n陳國勝",
    "校院名稱": "中央警察大學",
    "系所名稱": "水上警察研究所",
    "學位類別": "碩士",
    "畢業學年度": "108",
    "論文出版年": "2020"
  },
  {
    "序號": "172",
    "論文名稱": "未來海巡署遠洋漁業巡護的執勤能量提升規劃研究-以一千噸級巡護九號船為例",
    "研究生": "林益源",
    "指導教授": "吳東明",
    "校院名稱": "中央警察大學",
    "系所名稱": "水上警察研究所",
    "學位類別": "碩士",
    "畢業學年度": "108",
    "論文出版年": "2019"
  },
  {
    "序號": "173",
    "論文名稱": "禁止　限制水域內驅離大陸船舶相關問題之探討",
    "研究生": "趙子德",
    "指導教授": "姜皇池\n陳國勝",
    "校院名稱": "中央警察大學",
    "系所名稱": "水上警察研究所",
    "學位類別": "碩士",
    "畢業學年度": "108",
    "論文出版年": "2020"
  },
  {
    "序號": "174",
    "論文名稱": "論海岸巡防機關職權行使－以警察法為視角",
    "研究生": "莊進忠",
    "指導教授": "葉雲虎",
    "校院名稱": "中央警察大學",
    "系所名稱": "水上警察研究所",
    "學位類別": "碩士",
    "畢業學年度": "108",
    "論文出版年": "2019"
  },
  {
    "序號": "175",
    "論文名稱": "論酒後駕駛船舶之法規範與實踐",
    "研究生": "古家銘",
    "指導教授": "葉雲虎",
    "校院名稱": "中央警察大學",
    "系所名稱": "水上警察研究所",
    "學位類別": "碩士",
    "畢業學年度": "108",
    "論文出版年": "2019"
  },
  {
    "序號": "176",
    "論文名稱": "論使用衛星定位系統GPS偵查犯罪之適法性研究：以最高法院106年度台上字第3788號判決為中心",
    "研究生": "王藝儒",
    "指導教授": "姜皇池\n陳國勝",
    "校院名稱": "中央警察大學",
    "系所名稱": "水上警察研究所",
    "學位類別": "碩士",
    "畢業學年度": "109",
    "論文出版年": "2021"
  },
  {
    "序號": "177",
    "論文名稱": "論海岸巡防機關執行漁港安全檢查船筏評鑑制度",
    "研究生": "鍾開沛",
    "指導教授": "吳東明",
    "校院名稱": "中央警察大學",
    "系所名稱": "水上警察研究所",
    "學位類別": "碩士",
    "畢業學年度": "109",
    "論文出版年": "2021"
  },
  {
    "序號": "178",
    "論文名稱": "我國海上交通肇事逃逸問題之研究-以管轄權及行政處罰為中心",
    "研究生": "周祈志",
    "指導教授": "姜皇池\n劉春暉",
    "校院名稱": "中央警察大學",
    "系所名稱": "水上警察研究所",
    "學位類別": "碩士",
    "畢業學年度": "109",
    "論文出版年": "2020"
  },
  {
    "序號": "179",
    "論文名稱": "論國家海洋公園的設置與管理－以南方四島國家公園為例",
    "研究生": "李佳衡",
    "指導教授": "姜皇池\n葉雲虎",
    "校院名稱": "中央警察大學",
    "系所名稱": "水上警察研究所",
    "學位類別": "碩士",
    "畢業學年度": "109",
    "論文出版年": "2020"
  },
  {
    "序號": "180",
    "論文名稱": "海巡機關於內陸地區調查犯罪之研究",
    "研究生": "陳正辰",
    "指導教授": "姜皇池\n陳國勝",
    "校院名稱": "中央警察大學",
    "系所名稱": "水上警察研究所",
    "學位類別": "碩士",
    "畢業學年度": "109",
    "論文出版年": "2021"
  },
  {
    "序號": "181",
    "論文名稱": "海巡機關風災期間執行海岸警戒區域管制之研究—以權限衝突為中心",
    "研究生": "顏偉晉",
    "指導教授": "姜皇池\n陳國勝",
    "校院名稱": "中央警察大學",
    "系所名稱": "水上警察研究所",
    "學位類別": "碩士",
    "畢業學年度": "109",
    "論文出版年": "2021"
  },
  {
    "序號": "182",
    "論文名稱": "海洋空間規劃制度之國外實踐借鏡-以英國蘇格蘭案例為中心",
    "研究生": "洪毅帆",
    "指導教授": "吳東明",
    "校院名稱": "中央警察大學",
    "系所名稱": "水上警察研究所",
    "學位類別": "碩士",
    "畢業學年度": "109",
    "論文出版年": "2021"
  },
  {
    "序號": "183",
    "論文名稱": "我國海洋塑膠垃圾防治工作的探討與展望",
    "研究生": "吳冠明",
    "指導教授": "吳東明",
    "校院名稱": "中央警察大學",
    "系所名稱": "水上警察研究所",
    "學位類別": "碩士",
    "畢業學年度": "109",
    "論文出版年": "2021"
  },
  {
    "序號": "184",
    "論文名稱": "論沒入大陸船舶之研究—以《兩岸人民關係條例》與《行政罰法》適用分析為核心",
    "研究生": "羅平",
    "指導教授": "姜皇池\n陳國勝",
    "校院名稱": "中央警察大學",
    "系所名稱": "水上警察研究所",
    "學位類別": "碩士",
    "畢業學年度": "109",
    "論文出版年": "2021"
  },
  {
    "序號": "185",
    "論文名稱": "我國船舶交通服務制度發展規劃─以彰化風場航道VTS為例",
    "研究生": "吳波",
    "指導教授": "蔡奇呈",
    "校院名稱": "中央警察大學",
    "系所名稱": "水上警察研究所",
    "學位類別": "碩士",
    "畢業學年度": "110",
    "論文出版年": "2022"
  },
  {
    "序號": "186",
    "論文名稱": "論我國專屬經濟海域非生物資源之管理-以海底電纜為中心",
    "研究生": "沈明賢",
    "指導教授": "葉雲虎",
    "校院名稱": "中央警察大學",
    "系所名稱": "水上警察研究所",
    "學位類別": "碩士",
    "畢業學年度": "110",
    "論文出版年": "2022"
  },
  {
    "序號": "187",
    "論文名稱": "強化海巡艦船規劃暨後勤管理之探討—以海巡專屬公務碼頭籌獲為例",
    "研究生": "陳泗川",
    "指導教授": "吳東明",
    "校院名稱": "中央警察大學",
    "系所名稱": "水上警察研究所",
    "學位類別": "碩士",
    "畢業學年度": "110",
    "論文出版年": "2022"
  },
  {
    "序號": "188",
    "論文名稱": "海巡機關人力培訓資源之整合研究-以海洋委員會各訓練單位為探討中心",
    "研究生": "張晴奕",
    "指導教授": "劉春暉",
    "校院名稱": "中央警察大學",
    "系所名稱": "水上警察研究所",
    "學位類別": "碩士",
    "畢業學年度": "110",
    "論文出版年": "2022"
  },
  {
    "序號": "189",
    "論文名稱": "海巡機關運用無人機從事犯罪偵查之適法性分析-以美國為例",
    "研究生": "許雰嵐",
    "指導教授": "葉雲虎",
    "校院名稱": "中央警察大學",
    "系所名稱": "水上警察研究所",
    "學位類別": "碩士",
    "畢業學年度": "110",
    "論文出版年": "2022"
  },
  {
    "序號": "190",
    "論文名稱": "我國重大海洋污染緊急應變機制之研究-以美國海岸防衛隊ICS為參考",
    "研究生": "姚立仁",
    "指導教授": "劉春暉",
    "校院名稱": "中央警察大學",
    "系所名稱": "水上警察研究所",
    "學位類別": "碩士",
    "畢業學年度": "111",
    "論文出版年": "2023"
  },
  {
    "序號": "191",
    "論文名稱": "4000噸級巡防艦海上遠距醫療及緊急救護之研究-以CGICS海巡智慧船舶指揮管理系統為鏈路",
    "研究生": "鄭光佑",
    "指導教授": "劉春暉",
    "校院名稱": "中央警察大學",
    "系所名稱": "水上警察研究所",
    "學位類別": "碩士",
    "畢業學年度": "111",
    "論文出版年": "2023"
  },
  {
    "序號": "192",
    "論文名稱": "論制定海上秩序維護法之可行性-以社會秩序維護法為參考",
    "研究生": "朱炫璋",
    "指導教授": "陳國勝\n姜皇池",
    "校院名稱": "中央警察大學",
    "系所名稱": "水上警察研究所",
    "學位類別": "碩士",
    "畢業學年度": "111",
    "論文出版年": "2023"
  },
  {
    "序號": "193",
    "論文名稱": "中國行政處罰責任要件之演進─從《中國海警法》第35條舉證責任分配制度觀察",
    "研究生": "陳思伃",
    "指導教授": "陳國勝\n姜皇池",
    "校院名稱": "中央警察大學",
    "系所名稱": "水上警察研究所",
    "學位類別": "碩士",
    "畢業學年度": "111",
    "論文出版年": "2023"
  },
  {
    "序號": "194",
    "論文名稱": "越界大陸漁船留置與收容程序間執行階段之研究",
    "研究生": "蔡承晏",
    "指導教授": "葉雲虎",
    "校院名稱": "中央警察大學",
    "系所名稱": "水上警察研究所",
    "學位類別": "碩士",
    "畢業學年度": "111",
    "論文出版年": "2023"
  },
  {
    "序號": "195",
    "論文名稱": "我國海巡國際合作事務之現況探討及未來發展規劃",
    "研究生": "蘇俊維",
    "指導教授": "吳東明",
    "校院名稱": "中央警察大學",
    "系所名稱": "水上警察研究所",
    "學位類別": "碩士",
    "畢業學年度": "111",
    "論文出版年": "2023"
  },
  {
    "序號": "196",
    "論文名稱": "中國海上民兵之研究與因應",
    "研究生": "陳又豪",
    "指導教授": "姜皇池\n陳國勝",
    "校院名稱": "中央警察大學",
    "系所名稱": "水上警察研究所",
    "學位類別": "碩士",
    "畢業學年度": "111",
    "論文出版年": "2023"
  },
  {
    "序號": "197",
    "論文名稱": "海巡機關查緝海洋保育類野生動物非法案件—犯罪模式分析之研究",
    "研究生": "林彥慶",
    "指導教授": "吳東明",
    "校院名稱": "中央警察大學",
    "系所名稱": "水上警察研究所",
    "學位類別": "碩士",
    "畢業學年度": "111",
    "論文出版年": "2022"
  },
  {
    "序號": "198",
    "論文名稱": "論歐盟公海漁業養護與管理制度之研究─以打擊IUU捕魚行為之措施為探討核心",
    "研究生": "龔致榮",
    "指導教授": "葉雲虎",
    "校院名稱": "中央警察大學",
    "系所名稱": "水上警察研究所",
    "學位類別": "碩士",
    "畢業學年度": "112",
    "論文出版年": "2024"
  },
  {
    "序號": "199",
    "論文名稱": "論海巡機關組織變革下的機關定位之研究",
    "研究生": "歐玉朗",
    "指導教授": "葉雲虎",
    "校院名稱": "中央警察大學",
    "系所名稱": "水上警察研究所",
    "學位類別": "碩士",
    "畢業學年度": "112",
    "論文出版年": "2024"
  },
  {
    "序號": "200",
    "論文名稱": "平戰轉換政策下海巡人員戰時角色分析",
    "研究生": "曲平",
    "指導教授": "姜皇池\n陳國勝",
    "校院名稱": "中央警察大學",
    "系所名稱": "水上警察研究所",
    "學位類別": "碩士",
    "畢業學年度": "112",
    "論文出版年": "2024"
  },
  {
    "序號": "201",
    "論文名稱": "臺灣海峽劃設海上排除區可行性分析",
    "研究生": "陳俊霖",
    "指導教授": "姜皇池\n陳國勝",
    "校院名稱": "中央警察大學",
    "系所名稱": "水上警察研究所",
    "學位類別": "碩士",
    "畢業學年度": "112",
    "論文出版年": "2024"
  },
  {
    "序號": "202",
    "論文名稱": "海域執法使用低致命武器規範之研究",
    "研究生": "魏宏哲",
    "指導教授": "姜皇池\n陳國勝",
    "校院名稱": "中央警察大學",
    "系所名稱": "水上警察研究所",
    "學位類別": "碩士",
    "畢業學年度": "112",
    "論文出版年": "2023"
  },
  {
    "序號": "203",
    "論文名稱": "台灣北部漁場海域之漁汛期執法策略探析—以萬里蟳蟹季及蘇澳黑鮪魚季為例",
    "研究生": "徐漢慶",
    "指導教授": "吳東明",
    "校院名稱": "中央警察大學",
    "系所名稱": "水上警察研究所",
    "學位類別": "碩士",
    "畢業學年度": "112",
    "論文出版年": "2023"
  },
  {
    "序號": "204",
    "論文名稱": "我國海域意識政策建構之未來發展規劃",
    "研究生": "黃啓倫",
    "指導教授": "吳東明",
    "校院名稱": "中央警察大學",
    "系所名稱": "水上警察研究所",
    "學位類別": "碩士",
    "畢業學年度": "113",
    "論文出版年": "2024"
  },
  {
    "序號": "205",
    "論文名稱": "海巡艦船艇輪機系統的操作訓練標準化研究-以和平級艦為例",
    "研究生": "蔡武乾",
    "指導教授": "吳東明",
    "校院名稱": "中央警察大學",
    "系所名稱": "水上警察研究所",
    "學位類別": "碩士",
    "畢業學年度": "113",
    "論文出版年": "2024"
  }
]